outlier_101883055/__init__.py
outlier_101883055/outlier-removal.py
Outlier_Removal_Naman_Goyal-0.0.1.dist-info/LICENSE
Outlier_Removal_Naman_Goyal-0.0.1.dist-info/METADATA
Outlier_Removal_Naman_Goyal-0.0.1.dist-info/WHEEL
Outlier_Removal_Naman_Goyal-0.0.1.dist-info/top_level.txt
Outlier_Removal_Naman_Goyal-0.0.1.dist-info/RECORD
