Metadata-Version: 2.1
Name: Outlier-Removal-Naman-Goyal
Version: 0.0.1
Summary: Outlier Removal in the dataset using Z-score method 
Home-page: https://github.com/pypa/sampleproject
Author: Naman Goyal
Author-email: ngoyal_be17@thapar.edu
License: UNKNOWN
Platform: UNKNOWN
Classifier: Programming Language :: Python :: 3
Classifier: License :: OSI Approved :: MIT License
Classifier: Operating System :: OS Independent
Requires-Python: >=3
